README.md
setup.py
cov_bsv/__init__.py
cov_bsv/document_classifier.py
cov_bsv/util.py
cov_bsv.egg-info/PKG-INFO
cov_bsv.egg-info/SOURCES.txt
cov_bsv.egg-info/dependency_links.txt
cov_bsv.egg-info/requires.txt
cov_bsv.egg-info/top_level.txt
cov_bsv/knowledge_base/__init__.py
cov_bsv/knowledge_base/callbacks.py
cov_bsv/knowledge_base/concept_tag_rules.py
cov_bsv/knowledge_base/context_rules.py
cov_bsv/knowledge_base/postprocess_rules.py
cov_bsv/knowledge_base/preprocess_rules.py
cov_bsv/knowledge_base/section_rules.py
cov_bsv/knowledge_base/target_rules.py