Metadata-Version: 2.1
Name: cov-bsv
Version: 0.0.1.4
Summary: An NLP pipeline for COVID-19 surveillance used in the Department of Veterans Affairs Biosurveillance.
Home-page: UNKNOWN
Author: alec.chapman
Author-email: alec.chapman@hsc.utah.edu
License: UNKNOWN
Platform: UNKNOWN
